MANIFEST.in
README
setup.py
visql/__init__.py
visql/main.py
visql.egg-info/PKG-INFO
visql.egg-info/SOURCES.txt
visql.egg-info/dependency_links.txt
visql.egg-info/entry_points.txt
visql.egg-info/requires.txt
visql.egg-info/top_level.txt