Metadata-Version: 1.0
Name: visql
Version: 0.1.1
Summary: Edit a slice of a SQL database in vi
Home-page: https://github.com/paulfitz/visql
Author: Paul Fitzpatrick
Author-email: paulfitz@alum.mit.edu
License: UNKNOWN
Platform: UNKNOWN
